{"name":"build-javascript","namedChunkGroups":{"app":{"name":"app","assets":[{"name":"webpack-runtime-4f8dad5a33894a211ed3.js","size":3990},{"name":"framework-959189c965e8f0491b79.js","size":141014},{"name":"styles.7b178382b0042189ac1e.css","size":5977},{"name":"app-0ec83fc0e35286fb29de.js","size":75120}],"filteredAssets":0,"assetsSize":226101,"filteredAuxiliaryAssets":3,"auxiliaryAssetsSize":656271},"component---src-pages-404-js":{"name":"component---src-pages-404-js","assets":[{"name":"component---src-pages-404-js-fceb07a36e2569ee57a7.js","size":771}],"filteredAssets":0,"assetsSize":771,"filteredAuxiliaryAssets":1,"auxiliaryAssetsSize":1951},"component---src-pages-en-js":{"name":"component---src-pages-en-js","assets":[{"name":"framework-959189c965e8f0491b79.js","size":141014},{"name":"23918f63-d84741caad271b767b13.js","size":3378},{"name":"c1dcaf347079c47bccdc10c1be120605aa7ef23a-132e91c0b1fb8a669159.js","size":63404}],"filteredAssets":0,"assetsSize":207796,"filteredAuxiliaryAssets":4,"auxiliaryAssetsSize":3740210},"component---src-pages-index-js":{"name":"component---src-pages-index-js","assets":[{"name":"framework-959189c965e8f0491b79.js","size":141014},{"name":"23918f63-d84741caad271b767b13.js","size":3378},{"name":"c1dcaf347079c47bccdc10c1be120605aa7ef23a-132e91c0b1fb8a669159.js","size":63404},{"name":"component---src-pages-index-js-7b5cba13bda80bbfef04.js","size":21757}],"filteredAssets":0,"assetsSize":229553,"filteredAuxiliaryAssets":5,"auxiliaryAssetsSize":3779243}},"assetsByChunkName":{"app":["webpack-runtime-4f8dad5a33894a211ed3.js","framework-959189c965e8f0491b79.js","styles.7b178382b0042189ac1e.css","app-0ec83fc0e35286fb29de.js"],"component---src-pages-404-js":["component---src-pages-404-js-fceb07a36e2569ee57a7.js"],"component---src-pages-en-js":["framework-959189c965e8f0491b79.js","23918f63-d84741caad271b767b13.js","c1dcaf347079c47bccdc10c1be120605aa7ef23a-132e91c0b1fb8a669159.js"],"component---src-pages-index-js":["framework-959189c965e8f0491b79.js","23918f63-d84741caad271b767b13.js","c1dcaf347079c47bccdc10c1be120605aa7ef23a-132e91c0b1fb8a669159.js","component---src-pages-index-js-7b5cba13bda80bbfef04.js"]},"childAssetsByChunkName":{}}